Workbook
Name aporte: APP!$D$17
Name aporte_manual: APP!$I$13
Name inflacao_anual: APP!$I$14
Name patrimonio: APP!$D$20
Name perc_investimento: APP!$I$12
Name perfil: APP!$C$30
Name qtd_anos: APP!$D$18
Name rendimento_carteira: APP!$D$13
Name salario: APP!$D$12
Name sugestao_investimento: APP!$D$14
Name taxa_mensal: APP!$D$19

Sheet APP
B11: CONFIGURAÇÕES | F11: PREMISSAS
B12: Salário | D12: 8000 | F12: Percentual do salário a investir | I12: 0.3
B13: Rendimento Carteira | D13: 0.006 | F13: Aporte manual (opcional)
B14: ="Sugestão de Investimento ("&TEXT(perc_investimento,"0%")&")" -> Sugestão de Investimento (30%) | D14: =salario*perc_investimento -> 2400 | F14: Inflação anual estimada | I14: 0.045
B16: INVESTIMENTO MENSAL | F16: ANÁLISE DO PERÍODO
B17: Quanto investir por mês ? | D17: =IF(ISBLANK(aporte_manual),sugestao_investimento,aporte_manual) -> 2400 | F17: Rendimento carteira ao ano | I17: =(1+rendimento_carteira)^12-1 -> 0.074424168
B18: Por Quantos Anos ? | D18: 5 | F18: Taxa de rendimento ao ano | I18: =(1+taxa_mensal)^12-1 -> 0.13744718
B19: Taxa de Rendimento mensal ? | D19: 0.01079 | F19: Total aportado no período | I19: =aporte*qtd_anos*12 -> 144000
B20: Patrimônio acumulado ? | D20: =IFERROR(FV(taxa_mensal,qtd_anos*12,-aporte),0) -> 201064.59 | F20: Juros acumulados | I20: =patrimonio-I19 -> 57064.594
B21: Dividendos Mensais ? | D21: =patrimonio*rendimento_carteira -> 1206.3876 | F21: Patrimônio em valor de hoje | I21: =patrimonio/(1+inflacao_anual)^qtd_anos -> 161344.49
A23: Anos | B23: Cenários | D23: Dividendo | F23: Total aportado | G23: Juros | H23: % juros | I23: Valor de hoje
A24: 2 | B24: ="Quanto em "&A24&" Anos ?" -> Quanto em 2 Anos ? | C24: =IFERROR(FV(taxa_mensal,$A24*12,-aporte),0) -> 65346.306 | D24: =C24*rendimento_carteira -> 392.07783 | F24: =aporte*$A24*12 -> 57600 | G24: =C24-F24 -> 7746.3055 | H24: =IF(C24=0,0,G24/C24) -> 0.11854236 | I24: =C24/(1+inflacao_anual)^$A24 -> 59839.569
A25: 5 | B25: ="Quanto em "&A25&" Anos ?" -> Quanto em 5 Anos ? | C25: =IFERROR(FV(taxa_mensal,$A25*12,-aporte),0) -> 201064.59 | D25: =C25*rendimento_carteira -> 1206.3876 | F25: =aporte*$A25*12 -> 144000 | G25: =C25-F25 -> 57064.594 | H25: =IF(C25=0,0,G25/C25) -> 0.28381224 | I25: =C25/(1+inflacao_anual)^$A25 -> 161344.49
A26: 10 | B26: ="Quanto em "&A26&" Anos ?" -> Quanto em 10 Anos ? | C26: =IFERROR(FV(taxa_mensal,$A26*12,-aporte),0) -> 583882.11 | D26: =C26*rendimento_carteira -> 3503.2927 | F26: =aporte*$A26*12 -> 288000 | G26: =C26-F26 -> 295882.11 | H26: =IF(C26=0,0,G26/C26) -> 0.50674974 | I26: =C26/(1+inflacao_anual)^$A26 -> 375977.85
A27: 20 | B27: ="Quanto em "&A27&" Anos ?" -> Quanto em 20 Anos ? | C27: =IFERROR(FV(taxa_mensal,$A27*12,-aporte),0) -> 2700476.2 | D27: =C27*rendimento_carteira -> 16202.857 | F27: =aporte*$A27*12 -> 576000 | G27: =C27-F27 -> 2124476.2 | H27: =IF(C27=0,0,G27/C27) -> 0.78670428 | I27: =C27/(1+inflacao_anual)^$A27 -> 1119733.2
A28: 30 | B28: ="Quanto em "&A28&" Anos ?" -> Quanto em 30 Anos ? | C28: =IFERROR(FV(taxa_mensal,$A28*12,-aporte),0) -> 10373207 | D28: =C28*rendimento_carteira -> 62239.243 | F28: =aporte*$A28*12 -> 864000 | G28: =C28-F28 -> 9509207.2 | H28: =IF(C28=0,0,G28/C28) -> 0.9167085 | I28: =C28/(1+inflacao_anual)^$A28 -> 2769646.5
B30: PERFIL -----> | C30: Conservador
B31: VALOR A SER INVESTIDO POR MÊS | C31: =aporte -> 2400
B33: TIPO DE FII | C33: Percentual Sugerido | D33: Valores | F33: VERIFICAÇÃO
B34: PAPEL | C34: =IFERROR(VLOOKUP(TRIM(perfil)&"-"&B34,AUX!$A:$D,4,FALSE),0) -> 0.3 | D34: =C34*$C$31 -> 720 | F34: =IF(COUNTIF(AUX!$B:$B,TRIM(perfil))=0,"ATENÇÃO: perfil inválido",IF(ROUND(C40,4)<>1,"ATENÇÃO: percentuais do perfil somam "&TEXT(C40,"0%"),IF(ROUND(D40-C31,2)<>0,"ATENÇÃO: total difere do aporte","OK: alocação soma 100% do aporte"))) -> OK: alocação soma 100% do aporte
B35: TIJOLO | C35: =IFERROR(VLOOKUP(TRIM(perfil)&"-"&B35,AUX!$A:$D,4,FALSE),0) -> 0.5 | D35: =C35*$C$31 -> 1200
B36: HÍBRIDOS | C36: =IFERROR(VLOOKUP(TRIM(perfil)&"-"&B36,AUX!$A:$D,4,FALSE),0) -> 0.1 | D36: =C36*$C$31 -> 240
B37: FOFs | C37: =IFERROR(VLOOKUP(TRIM(perfil)&"-"&B37,AUX!$A:$D,4,FALSE),0) -> 0.1 | D37: =C37*$C$31 -> 240
B38: DESENVOLVIMENTO | C38: =IFERROR(VLOOKUP(TRIM(perfil)&"-"&B38,AUX!$A:$D,4,FALSE),0) -> 0 | D38: =C38*$C$31 -> 0
B39: HOTELARIAS | C39: =IFERROR(VLOOKUP(TRIM(perfil)&"-"&B39,AUX!$A:$D,4,FALSE),0) -> 0 | D39: =C39*$C$31 -> 0
B40: TOTAL | C40: =SUM(C34:C39) -> 1 | D40: =SUM(D34:D39) -> 2400
B56: NOTAS
B57: 1. Células em negrito sem preenchimento são entradas; as demais são calculadas.
B58: 2. Taxa de rendimento mensal (D19) = retorno total, usada para projetar o patrimônio. Rendimento carteira (D13) = dividend yield, usado para estimar a renda.
B59: 3. Valores futuros são nominais; a coluna "Valor de hoje" desconta a inflação estimada (I14). Não considera IR, taxas ou custos.
B60: 4. Os percentuais de alocação por perfil ficam na aba AUX e devem somar 100% (conferência em AUX!G8:I10).

Sheet AUX
A2: CHAVE | B2: PERFIL | C2: TIPO DE FII | D2: %
A3: =B3&"-"&C3 -> Conservador-PAPEL | B3: Conservador | C3: PAPEL | D3: 0.3 | G3: TESTE DE BUSCA | H3: %
A4: =B4&"-"&C4 -> Conservador-TIJOLO | B4: Conservador | C4: TIJOLO | D4: 0.5 | G4: Moderado-TIJOLO | H4: =VLOOKUP(G4,$A:$D,4,FALSE) -> 0.35
A5: =B5&"-"&C5 -> Conservador-HÍBRIDOS | B5: Conservador | C5: HÍBRIDOS | D5: 0.1
A6: =B6&"-"&C6 -> Conservador-FOFs | B6: Conservador | C6: FOFs | D6: 0.1
A7: =B7&"-"&C7 -> Conservador-DESENVOLVIMENTO | B7: Conservador | C7: DESENVOLVIMENTO | D7: 0 | G7: CONFERÊNCIA | H7: Soma % | I7: Status
A8: =B8&"-"&C8 -> Conservador-HOTELARIAS | B8: Conservador | C8: HOTELARIAS | D8: 0 | G8: Conservador | H8: =SUMIF($B:$B,G8,$D:$D) -> 1 | I8: =IF(ROUND(H8,4)=1,"OK","Ajustar") -> OK
A9: =B9&"-"&C9 -> Moderado-PAPEL | B9: Moderado | C9: PAPEL | D9: 0.32 | G9: Moderado | H9: =SUMIF($B:$B,G9,$D:$D) -> 1 | I9: =IF(ROUND(H9,4)=1,"OK","Ajustar") -> OK
A10: =B10&"-"&C10 -> Moderado-TIJOLO | B10: Moderado | C10: TIJOLO | D10: 0.35 | G10: Agressivo | H10: =SUMIF($B:$B,G10,$D:$D) -> 1 | I10: =IF(ROUND(H10,4)=1,"OK","Ajustar") -> OK
A11: =B11&"-"&C11 -> Moderado-HÍBRIDOS | B11: Moderado | C11: HÍBRIDOS | D11: 0.08
A12: =B12&"-"&C12 -> Moderado-FOFs | B12: Moderado | C12: FOFs | D12: 0.05
A13: =B13&"-"&C13 -> Moderado-DESENVOLVIMENTO | B13: Moderado | C13: DESENVOLVIMENTO | D13: 0.1
A14: =B14&"-"&C14 -> Moderado-HOTELARIAS | B14: Moderado | C14: HOTELARIAS | D14: 0.1
A15: =B15&"-"&C15 -> Agressivo-PAPEL | B15: Agressivo | C15: PAPEL | D15: 0.5
A16: =B16&"-"&C16 -> Agressivo-TIJOLO | B16: Agressivo | C16: TIJOLO | D16: 0.1
A17: =B17&"-"&C17 -> Agressivo-HÍBRIDOS | B17: Agressivo | C17: HÍBRIDOS | D17: 0.05
A18: =B18&"-"&C18 -> Agressivo-FOFs | B18: Agressivo | C18: FOFs | D18: 0.05
A19: =B19&"-"&C19 -> Agressivo-DESENVOLVIMENTO | B19: Agressivo | C19: DESENVOLVIMENTO | D19: 0.2
A20: =B20&"-"&C20 -> Agressivo-HOTELARIAS | B20: Agressivo | C20: HOTELARIAS | D20: 0.1
